aiohomematic/__init__.py
aiohomematic/_log_context_protocol.py
aiohomematic/api.py
aiohomematic/async_support.py
aiohomematic/backend_detection.py
aiohomematic/compat.py
aiohomematic/const.py
aiohomematic/context.py
aiohomematic/converter.py
aiohomematic/decorators.py
aiohomematic/exceptions.py
aiohomematic/hmcli.py
aiohomematic/i18n.py
aiohomematic/logging_context.py
aiohomematic/property_decorators.py
aiohomematic/py.typed
aiohomematic/strings.json
aiohomematic/support.py
aiohomematic/tracing.py
aiohomematic/type_aliases.py
aiohomematic/validator.py
aiohomematic/central/__init__.py
aiohomematic/central/central_unit.py
aiohomematic/central/config.py
aiohomematic/central/config_builder.py
aiohomematic/central/connection_state.py
aiohomematic/central/decorators.py
aiohomematic/central/device_registry.py
aiohomematic/central/health.py
aiohomematic/central/registry.py
aiohomematic/central/rpc_server.py
aiohomematic/central/scheduler.py
aiohomematic/central/state_machine.py
aiohomematic/central/coordinators/__init__.py
aiohomematic/central/coordinators/cache.py
aiohomematic/central/coordinators/client.py
aiohomematic/central/coordinators/connection_recovery.py
aiohomematic/central/coordinators/device.py
aiohomematic/central/coordinators/event.py
aiohomematic/central/coordinators/hub.py
aiohomematic/central/events/__init__.py
aiohomematic/central/events/bus.py
aiohomematic/central/events/integration.py
aiohomematic/central/events/types.py
aiohomematic/client/__init__.py
aiohomematic/client/_rpc_errors.py
aiohomematic/client/circuit_breaker.py
aiohomematic/client/client_factory.py
aiohomematic/client/config.py
aiohomematic/client/interface_client.py
aiohomematic/client/json_rpc.py
aiohomematic/client/request_coalescer.py
aiohomematic/client/rpc_proxy.py
aiohomematic/client/state_change.py
aiohomematic/client/state_machine.py
aiohomematic/client/backends/__init__.py
aiohomematic/client/backends/base.py
aiohomematic/client/backends/capabilities.py
aiohomematic-2026.2.0.dist-info/licenses/LICENSE
aiohomematic-2026.2.0.dist-info/METADATA
aiohomematic-2026.2.0.dist-info/WHEEL
aiohomematic-2026.2.0.dist-info/entry_points.txt
aiohomematic-2026.2.0.dist-info/top_level.txt
aiohomematic-2026.2.0.dist-info/RECORD
