Metadata-Version: 2.4
Name: aiohomematic
Version: 2026.2.0
Summary: Homematic interface for Home Assistant running on Python 3.
Home-page: https://github.com/sukramj/aiohomematic
Author-email: SukramJ <sukramj@icloud.com>, Daniel Perna <danielperna84@gmail.com>
License: MIT License
Project-URL: Homepage, https://github.com/sukramj/aiohomematic
Project-URL: Source Code, https://github.com/sukramj/aiohomematic
Project-URL: Bug Reports, https://github.com/sukramj/aiohomematic/issues
Project-URL: Changelog, https://github.com/sukramj/aiohomematic/blob/devel/changelog.md
Project-URL: Documentation, https://sukramj.github.io/aiohomematic
Project-URL: Forum, https://github.com/sukramj/aiohomematic/discussions
Keywords: home,automation,homematic,openccu,homegear
Classifier: Development Status :: 5 - Production/Stable
Classifier: Environment :: No Input/Output (Daemon)
Classifier: Intended Audience :: End Users/Desktop
Classifier: Intended Audience :: Developers
Classifier: License :: OSI Approved :: MIT License
Classifier: Natural Language :: English
Classifier: Natural Language :: German
Classifier: Operating System :: OS Independent
Classifier: Programming Language :: Python
Classifier: Programming Language :: Python :: 3
Classifier: Programming Language :: Python :: 3 :: Only
Classifier: Programming Language :: Python :: 3.13
Classifier: Programming Language :: Python :: 3.14
Classifier: Programming Language :: Python :: Free Threading :: 2 - Beta
Classifier: Programming Language :: Python :: Implementation :: CPython
Classifier: Framework :: AsyncIO
Classifier: Topic :: Home Automation
Classifier: Topic :: Software Development :: Libraries :: Python Modules
Classifier: Typing :: Typed
Requires-Python: >=3.13
License-File: LICENSE
Requires-Dist: aiohttp>=3.12.0
Requires-Dist: pydantic>=2.10.0
Requires-Dist: python-slugify>=8.0.0
Provides-Extra: fast
Requires-Dist: orjson>=3.11.0; extra == "fast"
Dynamic: license-file
